{
    "filename": "cwrgm.org_files_large_d4c325b92a310a18cae59d4174aa0d06971da50e.jpg",
    "description": "Telegram from General J. Z. George to Mississippi Governor John J. Pettus; July 4, 1863",
    "tags": [
        "Confederate States of America. Army",
        "Jackson (Miss.)",
        "Pettus, John Jones, 1813-1867",
        "Telegraph Company",
        "Telegraph Company--South-Western Telegraph Company (Ky.)"
    ],
    "permalink": "https://cwrgm.org/files/large/d4c325b92a310a18cae59d4174aa0d06971da50e.jpg",
    "year": "1863"
}