{
    "filename": "cwrgm.org_files_large_c7742a1b5a04450aebcb345336c91fccac015a06.jpg",
    "description": "Telegram from Captain Posey Carnot to Adjutant General William H. Brown; May 6, 1861",
    "tags": [
        "Confederate States of America. Army",
        "Jackson (Miss.)",
        "Telegraph Company",
        "Telegraph Company--South-Western Telegraph Company (Ky.)"
    ],
    "permalink": "https://cwrgm.org/files/large/c7742a1b5a04450aebcb345336c91fccac015a06.jpg",
    "year": "1861"
}