{
    "filename": "cwrgm.org_files_large_e892557340ef336583d296d61066765813131e12.jpg",
    "description": "Telegram from G. D. Moore to Mississippi Governor John J. Pettus; June 27, 1863",
    "tags": [
        "Jackson (Miss.)",
        "Macon (Miss.)",
        "Pettus, John Jones, 1813-1867",
        "Telegraph Company",
        "Telegraph Company--South-Western Telegraph Company (Ky.)"
    ],
    "permalink": "https://cwrgm.org/files/large/e892557340ef336583d296d61066765813131e12.jpg",
    "year": "1863"
}